seapopym_optimization/__init__.py
seapopym_optimization/algorithm/__init__.py
seapopym_optimization/algorithm/genetic_algorithm/__init__.py
seapopym_optimization/algorithm/genetic_algorithm/evaluation_strategies.py
seapopym_optimization/algorithm/genetic_algorithm/factory.py
seapopym_optimization/algorithm/genetic_algorithm/genetic_algorithm.py
seapopym_optimization/algorithm/genetic_algorithm/logbook.py
seapopym_optimization/algorithm/protocol.py
seapopym_optimization/configuration_generator/__init__.py
seapopym_optimization/configuration_generator/acidity_configuration_generator.py
seapopym_optimization/configuration_generator/no_transport_configuration_generator.py
seapopym_optimization/configuration_generator/protocols.py
seapopym_optimization/constraint/__init__.py
seapopym_optimization/constraint/energy_transfert_constraint.py
seapopym_optimization/constraint/protocol.py
seapopym_optimization/cost_function/__init__.py
seapopym_optimization/cost_function/cost_function.py
seapopym_optimization/cost_function/metric.py
seapopym_optimization/cost_function/processor.py
seapopym_optimization/cost_function/protocol.py
seapopym_optimization/functional_group/__init__.py
seapopym_optimization/functional_group/acidity_functional_groups.py
seapopym_optimization/functional_group/base_functional_group.py
seapopym_optimization/functional_group/no_transport_functional_groups.py
seapopym_optimization/functional_group/parameter_initialization.py
seapopym_optimization/observations/__init__.py
seapopym_optimization/observations/observation.py
seapopym_optimization/observations/protocol.py
seapopym_optimization/observations/protocols.py
seapopym_optimization/observations/time_serie.py
seapopym_optimization/old_implementation/error_weighted_cost_function.py
seapopym_optimization/old_implementation/seasonality_cost_function.py
seapopym_optimization-0.0.2.3.dist-info/LICENSE
seapopym_optimization-0.0.2.3.dist-info/METADATA
seapopym_optimization-0.0.2.3.dist-info/WHEEL
seapopym_optimization-0.0.2.3.dist-info/RECORD
